cascade/__init__.py
cascade/data_preprocessing.py
cascade/model.py
cascade/run.py
cascade/split.py
cascade/utils.py
epicascade/__init__.py
epicascade/data_preprocessing.py
epicascade/model.py
epicascade/run.py
epicascade/split.py
epicascade/utils.py
epicascade-0.0.2.dist-info/LICENSE
epicascade-0.0.2.dist-info/METADATA
epicascade-0.0.2.dist-info/WHEEL
epicascade-0.0.2.dist-info/top_level.txt
epicascade-0.0.2.dist-info/RECORD
